README.rst
setup.py
RetryMe/__init__.py
RetryMe/logger.py
RetryMe/retryme.py
RetryMe.egg-info/PKG-INFO
RetryMe.egg-info/SOURCES.txt
RetryMe.egg-info/dependency_links.txt
RetryMe.egg-info/top_level.txt
test/test.py
test/test_result_retry.py
test/test_sleep_time_gen.py